{"name":"ubuntu","slug":"ubuntu","count":1,"postlist":[{"title":"ubuntu-multipass","uid":"ba590f4c595f20e0726c162dbce4dd2d","slug":"ubuntu-multipass","date":"2022-04-24T08:42:43.000Z","updated":"2022-06-02T08:46:03.037Z","comments":true,"path":"api/articles/ubuntu-multipass.json","keywords":null,"cover":"https://raw.githubusercontent.com/ITLab1024/picgo-images/main/202204241645651.png","text":"什么是Maultipass？ 官方说明： Ubuntu VMs on demand for any workstation Get an instant Ubuntu VM with a single command. Multipass can launch and run v...","link":"","photos":[],"count_time":{"symbolsCount":"2.7k","symbolsTime":"2 mins."},"categories":[{"name":"ubuntu","slug":"ubuntu","count":1,"path":"api/categories/ubuntu.json"},{"name":"multipass","slug":"ubuntu/multipass","count":1,"path":"api/categories/ubuntu/multipass.json"},{"name":"虚拟机","slug":"ubuntu/multipass/虚拟机","count":1,"path":"api/categories/ubuntu/multipass/虚拟机.json"}],"tags":[{"name":"multipass","slug":"multipass","count":1,"path":"api/tags/multipass.json"},{"name":"ubuntu","slug":"ubuntu","count":1,"path":"api/tags/ubuntu.json"}],"author":{"name":"ITLab","slug":"blog-author","avatar":"https://raw.githubusercontent.com/ITLab1024/picgo-images/main/202204221711395.png","link":"/","description":"梦想越是美丽，就越是显得遥不可及，可奇怪的是，一旦你下定了决心，很快地，那些梦想就一一成为了现实！","socials":{"github":"https://github.com/ITLab1024","twitter":"","stackoverflow":"","wechat":"","qq":"","weibo":"","zhihu":"https://www.zhihu.com/people/xpp1109","csdn":"","juejin":"","customs":{"wxgzh":{"icon":"fa fa-wechat","link":"https://raw.githubusercontent.com/ITLab1024/picgo-images/main/202204231828426.jpg"}}}},"feature":true}]}